camphr_models/__init__.py
camphr_models/download.py
camphr_models-0.1.0.dist-info/entry_points.txt
camphr_models-0.1.0.dist-info/WHEEL
camphr_models-0.1.0.dist-info/METADATA
camphr_models-0.1.0.dist-info/RECORD
