Metadata-Version: 2.1
Name: camphr-models
Version: 0.1.0
Summary: 
License: Apache-2.0
Author: Yohei Tamura
Author-email: tamuhey@gmail.com
Requires-Python: >=3.6,<4.0
Classifier: License :: OSI Approved :: Apache Software License
Classifier: Programming Language :: Python :: 3
Classifier: Programming Language :: Python :: 3.6
Classifier: Programming Language :: Python :: 3.7
Classifier: Programming Language :: Python :: 3.8
Requires-Dist: fire (>=0.2.1,<0.3.0)
